azure/communication/networktraversal/__init__.py
azure/communication/networktraversal/_api_versions.py
azure/communication/networktraversal/_communication_relay_client.py
azure/communication/networktraversal/_version.py
azure/communication/networktraversal/py.typed
azure/communication/networktraversal/_generated/__init__.py
azure/communication/networktraversal/_generated/_communication_network_traversal_client.py
azure/communication/networktraversal/_generated/_configuration.py
azure/communication/networktraversal/_generated/_patch.py
azure/communication/networktraversal/_generated/_vendor.py
azure/communication/networktraversal/_generated/aio/__init__.py
azure/communication/networktraversal/_generated/aio/_communication_network_traversal_client.py
azure/communication/networktraversal/_generated/aio/_configuration.py
azure/communication/networktraversal/_generated/aio/_patch.py
azure/communication/networktraversal/_generated/aio/operations/__init__.py
azure/communication/networktraversal/_generated/aio/operations/_communication_network_traversal_operations.py
azure/communication/networktraversal/_generated/models/__init__.py
azure/communication/networktraversal/_generated/models/_communication_network_traversal_client_enums.py
azure/communication/networktraversal/_generated/models/_models.py
azure/communication/networktraversal/_generated/models/_models_py3.py
azure/communication/networktraversal/_generated/operations/__init__.py
azure/communication/networktraversal/_generated/operations/_communication_network_traversal_operations.py
azure/communication/networktraversal/_shared/__init__.py
azure/communication/networktraversal/_shared/auth_policy_utils.py
azure/communication/networktraversal/_shared/models.py
azure/communication/networktraversal/_shared/policy.py
azure/communication/networktraversal/_shared/user_credential.py
azure/communication/networktraversal/_shared/user_credential_async.py
azure/communication/networktraversal/_shared/utils.py
azure_communication_networktraversal-1.1.0b2.dist-info/LICENSE
azure_communication_networktraversal-1.1.0b2.dist-info/METADATA
azure_communication_networktraversal-1.1.0b2.dist-info/WHEEL
azure_communication_networktraversal-1.1.0b2.dist-info/top_level.txt
azure_communication_networktraversal-1.1.0b2.dist-info/RECORD
