Metadata-Version: 2.1
Name: azure-communication-networktraversal
Version: 1.1.0b2
Summary: Microsoft Azure Communication Network Traversal Service Client Library for Python
Home-page: https://github.com/Azure/azure-sdk-for-python
Author: Microsoft Corporation
Author-email: azuresdkengsysadmins@microsoft.com
License: MIT License
Project-URL: Bug Reports, https://github.com/Azure/azure-sdk-for-python/issues
Project-URL: Source, https://github.com/Azure/azure-sdk-for-python
Keywords: azure,azure sdk
Classifier: Development Status :: 7 - Inactive
Classifier: Programming Language :: Python
Classifier: Programming Language :: Python :: 3 :: Only
Classifier: Programming Language :: Python :: 3
Classifier: Programming Language :: Python :: 3.8
Classifier: Programming Language :: Python :: 3.9
Classifier: Programming Language :: Python :: 3.10
Classifier: Programming Language :: Python :: 3.11
Classifier: Programming Language :: Python :: 3.12
Classifier: License :: OSI Approved :: MIT License
Requires-Python: >=3.8
License-File: LICENSE
Requires-Dist: msrest >=0.7.1
Requires-Dist: azure-core >=1.24.0
Requires-Dist: typing-extensions ; python_version<'3.8'
